akData/Cycle.py
akData/version.py
akData/__init__.py
akData/format/abn.py
akData/format/boolean.py
akData/format/datetime.py
akData/format/django.py
akData/format/number.py
akData/format/phoneNumber.py
akData/format/__init__.py
akData/parse/abn.py
akData/parse/phoneNumber.py
akData/parse/__init__.py
akData/validate/abn.py
akData/validate/__init__.py
akData-0.0.2.dist-info/DESCRIPTION.rst
akData-0.0.2.dist-info/METADATA
akData-0.0.2.dist-info/metadata.json
akData-0.0.2.dist-info/RECORD
akData-0.0.2.dist-info/top_level.txt
akData-0.0.2.dist-info/WHEEL
