Metadata-Version: 2.0
Name: akData
Version: 0.0.2
Summary: Data manipulation - formatting, parsing, validating and converting
Home-page: https://github.com/adamkerz/akData
Author: Adam Kerz
Author-email: adam@kerz.id.au
License: BSD 3-Clause
Keywords: data
Platform: UNKNOWN
Classifier: Development Status :: 4 - Beta
Classifier: Intended Audience :: Developers
Classifier: Natural Language :: English
Classifier: License :: OSI Approved :: BSD License
Classifier: Operating System :: OS Independent
Classifier: Programming Language :: Python
Classifier: Programming Language :: Python :: 2
Classifier: Programming Language :: Python :: 2.7
Classifier: Programming Language :: Python :: 3
Classifier: Programming Language :: Python :: 3.4
Classifier: Topic :: Software Development :: Libraries :: Python Modules
